DLStudio-2.5.5.html
MANIFEST.in
Makefile
README
setup.py
AdversarialLearning/AdversarialLearning.py
AdversarialLearning/__init__.py
DLStudio/DLStudio.py
DLStudio/__init__.py
DLStudio.egg-info/PKG-INFO
DLStudio.egg-info/SOURCES.txt
DLStudio.egg-info/dependency_links.txt
DLStudio.egg-info/top_level.txt
DataPrediction/DataPrediction.py
DataPrediction/__init__.py
Examples/README
Examples/custom_data_loading.py
Examples/noisy_object_detection_and_localization.py
Examples/object_detection_and_localization.py
Examples/object_detection_and_localization_iou.py
Examples/playing_with_cifar10.py
Examples/playing_with_reconfig.py
Examples/playing_with_sequential.py
Examples/playing_with_skip_connections.py
Examples/run_autoencoder.py
Examples/run_vae.py
Examples/run_vae_for_image_generation.py
Examples/run_vqgan.py
Examples/run_vqgan_map_image_to_codebook.py
Examples/run_vqgan_transformer.py
Examples/run_vqvae.py
Examples/semantic_segmentation.py
Examples/text_classification_with_GRU.py
Examples/text_classification_with_GRU_word2vec.py
Examples/text_classification_with_TEXTnet.py
Examples/text_classification_with_TEXTnetOrder2.py
Examples/text_classification_with_TEXTnetOrder2_word2vec.py
Examples/text_classification_with_TEXTnet_word2vec.py
ExamplesAdversarialLearning/README
ExamplesAdversarialLearning/dcgan_DG1.py
ExamplesAdversarialLearning/dcgan_DG2.py
ExamplesAdversarialLearning/wgan_CG1.py
ExamplesAdversarialLearning/wgan_with_gp_CG2.py
ExamplesDataPrediction/power_load_prediction_with_pmGRU.py
ExamplesDiffusion/GenerateNewImageSamples.py
ExamplesDiffusion/README
ExamplesDiffusion/RunCodeForDiffusion.py
ExamplesDiffusion/VisualizeSamples.py
ExamplesMetricLearning/example_for_pairwise_contrastive_loss.py
ExamplesMetricLearning/example_for_triplet_loss.py
ExamplesSeq2SeqLearning/seq2seq_with_learnable_embeddings.py
ExamplesSeq2SeqLearning/seq2seq_with_pretrained_embeddings.py
ExamplesTransformers/image_recog_with_visTransformer.py
ExamplesTransformers/run_autoencoder_with_transformer.py
ExamplesTransformers/seq2seq_with_transformerFG.py
ExamplesTransformers/seq2seq_with_transformerPreLN.py
