Metadata-Version: 2.1
Name: DLStudio
Version: 2.5.5
Summary: A PyTorch based software platform for teaching the Deep Learning class at Purdue University
Home-page: https://engineering.purdue.edu/kak/distDLS/DLStudio-2.5.5.html
Download-URL: https://engineering.purdue.edu/kak/distDLS/DLStudio-2.5.5.tar.gz
Author: Avinash Kak
Author-email: kak@purdue.edu
Maintainer: Avinash Kak
Maintainer-email: kak@purdue.edu
License: Python Software Foundation License
Keywords: PyTorch programming
Platform: All platforms
Classifier: Topic :: Scientific/Engineering
Classifier: Programming Language :: Python :: 3.10
